odoo8_addon_l10n_it_split_payment-8.0.1.0.1-nspkg.pth
odoo_addons/l10n_it_split_payment/README.rst
odoo_addons/l10n_it_split_payment/__init__.py
odoo_addons/l10n_it_split_payment/__openerp__.py
odoo_addons/l10n_it_split_payment/i18n/it.po
odoo_addons/l10n_it_split_payment/i18n/l10n_it_split_payment.pot
odoo_addons/l10n_it_split_payment/i18n/sl.po
odoo_addons/l10n_it_split_payment/models/__init__.py
odoo_addons/l10n_it_split_payment/models/account.py
odoo_addons/l10n_it_split_payment/models/config.py
odoo_addons/l10n_it_split_payment/security/ir.model.access.csv
odoo_addons/l10n_it_split_payment/static/SP.png
odoo_addons/l10n_it_split_payment/static/fiscal_position.png
odoo_addons/l10n_it_split_payment/static/description/icon.png
odoo_addons/l10n_it_split_payment/tests/__init__.py
odoo_addons/l10n_it_split_payment/tests/test_splitpayment.py
odoo_addons/l10n_it_split_payment/views/account_view.xml
odoo_addons/l10n_it_split_payment/views/config_view.xml
odoo8_addon_l10n_it_split_payment-8.0.1.0.1.dist-info/METADATA
odoo8_addon_l10n_it_split_payment-8.0.1.0.1.dist-info/WHEEL
odoo8_addon_l10n_it_split_payment-8.0.1.0.1.dist-info/namespace_packages.txt
odoo8_addon_l10n_it_split_payment-8.0.1.0.1.dist-info/top_level.txt
odoo8_addon_l10n_it_split_payment-8.0.1.0.1.dist-info/RECORD
